Metadata-Version: 2.1
Name: eloquentarduino
Version: 1.0.0
Summary: A wrapper for Edge Impulse Linux package
Home-page: https://github.com/eloquentarduino/eloquent-edge-impulse-python
Author: Simone Salerno
Author-email: eloquentarduino@gmail.com
License: MIT
Keywords: ML,Edge Impulse,Edge AI
License-File: LICENSE
